[{"date":"2018-11-21T00:00","casino":611,"sportbook":309,"other":324,"totalbet":7292},{"date":"2018-11-21T01:00","casino":737,"sportbook":311,"other":309,"totalbet":7849},{"date":"2018-11-21T02:00","casino":726,"sportbook":312,"other":219,"totalbet":7624},{"date":"2018-11-21T03:00","casino":651,"sportbook":269,"other":212,"totalbet":7859},{"date":"2018-11-21T04:00","casino":740,"sportbook":230,"other":239,"totalbet":6515},{"date":"2018-11-21T05:00","casino":748,"sportbook":214,"other":316,"totalbet":7538},{"date":"2018-11-21T06:00","casino":610,"sportbook":231,"other":315,"totalbet":6295},{"date":"2018-11-21T07:00","casino":610,"sportbook":276,"other":264,"totalbet":6722},{"date":"2018-11-21T08:00","casino":655,"sportbook":322,"other":210,"totalbet":7830},{"date":"2018-11-21T09:00","casino":692,"sportbook":219,"other":323,"totalbet":7670},{"date":"2018-11-21T10:00","casino":754,"sportbook":299,"other":222,"totalbet":6714},{"date":"2018-11-21T11:00","casino":623,"sportbook":232,"other":276,"totalbet":7535},{"date":"2018-11-21T12:00","casino":609,"sportbook":344,"other":298,"totalbet":6152},{"date":"2018-11-21T13:00","casino":799,"sportbook":220,"other":250,"totalbet":7660},{"date":"2018-11-21T14:00","casino":728,"sportbook":264,"other":317,"totalbet":6973},{"date":"2018-11-21T15:00","casino":742,"sportbook":318,"other":276,"totalbet":6497},{"date":"2018-11-21T16:00","casino":720,"sportbook":327,"other":234,"totalbet":6928},{"date":"2018-11-21T17:00","casino":785,"sportbook":253,"other":343,"totalbet":7036},{"date":"2018-11-21T18:00","casino":755,"sportbook":326,"other":339,"totalbet":6311},{"date":"2018-11-21T19:00","casino":730,"sportbook":315,"other":321,"totalbet":7956},{"date":"2018-11-21T20:00","casino":795,"sportbook":229,"other":292,"totalbet":7704},{"date":"2018-11-21T21:00","casino":794,"sportbook":230,"other":279,"totalbet":6251},{"date":"2018-11-21T22:00","casino":628,"sportbook":320,"other":206,"totalbet":6649},{"date":"2018-11-21T23:00","casino":776,"sportbook":313,"other":212,"totalbet":7297},{"date":"2018-11-22T00:00","casino":700,"sportbook":242,"other":301,"totalbet":6662},{"date":"2018-11-22T01:00","casino":759,"sportbook":284,"other":337,"totalbet":6386},{"date":"2018-11-22T02:00","casino":747,"sportbook":227,"other":288,"totalbet":6933},{"date":"2018-11-22T03:00","casino":624,"sportbook":306,"other":294,"totalbet":6074},{"date":"2018-11-22T04:00","casino":624,"sportbook":332,"other":249,"totalbet":6707},{"date":"2018-11-22T05:00","casino":651,"sportbook":293,"other":320,"totalbet":7521},{"date":"2018-11-22T06:00","casino":633,"sportbook":335,"other":343,"totalbet":6149},{"date":"2018-11-22T07:00","casino":772,"sportbook":248,"other":295,"totalbet":6819},{"date":"2018-11-22T08:00","casino":666,"sportbook":257,"other":341,"totalbet":7646},{"date":"2018-11-22T09:00","casino":796,"sportbook":225,"other":276,"totalbet":7681},{"date":"2018-11-22T10:00","casino":722,"sportbook":241,"other":222,"totalbet":6687},{"date":"2018-11-22T11:00","casino":684,"sportbook":309,"other":270,"totalbet":6377},{"date":"2018-11-22T12:00","casino":638,"sportbook":327,"other":251,"totalbet":6959},{"date":"2018-11-22T13:00","casino":755,"sportbook":278,"other":315,"totalbet":7568},{"date":"2018-11-22T14:00","casino":666,"sportbook":275,"other":203,"totalbet":6459},{"date":"2018-11-22T15:00","casino":778,"sportbook":336,"other":268,"totalbet":7970},{"date":"2018-11-22T16:00","casino":601,"sportbook":223,"other":213,"totalbet":7593},{"date":"2018-11-22T17:00","casino":637,"sportbook":208,"other":324,"totalbet":7094},{"date":"2018-11-22T18:00","casino":769,"sportbook":346,"other":298,"totalbet":7570},{"date":"2018-11-22T19:00","casino":783,"sportbook":230,"other":239,"totalbet":7865},{"date":"2018-11-22T20:00","casino":771,"sportbook":202,"other":219,"totalbet":6478},{"date":"2018-11-22T21:00","casino":779,"sportbook":307,"other":292,"totalbet":6360},{"date":"2018-11-22T22:00","casino":722,"sportbook":214,"other":273,"totalbet":6489},{"date":"2018-11-22T23:00","casino":749,"sportbook":237,"other":287,"totalbet":6489},{"date":"2018-11-23T00:00","casino":652,"sportbook":219,"other":309,"totalbet":7884},{"date":"2018-11-23T01:00","casino":666,"sportbook":235,"other":233,"totalbet":6342},{"date":"2018-11-23T02:00","casino":616,"sportbook":247,"other":242,"totalbet":6767},{"date":"2018-11-23T03:00","casino":661,"sportbook":289,"other":336,"totalbet":7090},{"date":"2018-11-23T04:00","casino":721,"sportbook":206,"other":302,"totalbet":6096},{"date":"2018-11-23T05:00","casino":759,"sportbook":286,"other":331,"totalbet":7372},{"date":"2018-11-23T06:00","casino":743,"sportbook":239,"other":214,"totalbet":6882},{"date":"2018-11-23T07:00","casino":627,"sportbook":287,"other":240,"totalbet":7915},{"date":"2018-11-23T08:00","casino":668,"sportbook":222,"other":293,"totalbet":6724},{"date":"2018-11-23T09:00","casino":740,"sportbook":228,"other":204,"totalbet":7631},{"date":"2018-11-23T10:00","casino":726,"sportbook":266,"other":251,"totalbet":7949},{"date":"2018-11-23T11:00","casino":683,"sportbook":289,"other":324,"totalbet":6444},{"date":"2018-11-23T12:00","casino":618,"sportbook":256,"other":271,"totalbet":6594},{"date":"2018-11-23T13:00","casino":755,"sportbook":331,"other":256,"totalbet":7250},{"date":"2018-11-23T14:00","casino":780,"sportbook":283,"other":268,"totalbet":6650},{"date":"2018-11-23T15:00","casino":768,"sportbook":221,"other":336,"totalbet":6185},{"date":"2018-11-23T16:00","casino":753,"sportbook":345,"other":348,"totalbet":7205},{"date":"2018-11-23T17:00","casino":725,"sportbook":285,"other":349,"totalbet":7208},{"date":"2018-11-23T18:00","casino":700,"sportbook":317,"other":348,"totalbet":6671},{"date":"2018-11-23T19:00","casino":776,"sportbook":221,"other":288,"totalbet":7601},{"date":"2018-11-23T20:00","casino":620,"sportbook":317,"other":249,"totalbet":6452},{"date":"2018-11-23T21:00","casino":664,"sportbook":325,"other":273,"totalbet":6033},{"date":"2018-11-23T22:00","casino":709,"sportbook":224,"other":296,"totalbet":6765},{"date":"2018-11-23T23:00","casino":763,"sportbook":318,"other":271,"totalbet":6652},{"date":"2018-11-24T00:00","casino":657,"sportbook":322,"other":265,"totalbet":6625},{"date":"2018-11-24T01:00","casino":743,"sportbook":297,"other":290,"totalbet":7229},{"date":"2018-11-24T02:00","casino":743,"sportbook":258,"other":212,"totalbet":7996},{"date":"2018-11-24T03:00","casino":749,"sportbook":221,"other":272,"totalbet":6648},{"date":"2018-11-24T04:00","casino":605,"sportbook":222,"other":283,"totalbet":6583},{"date":"2018-11-24T05:00","casino":710,"sportbook":350,"other":300,"totalbet":7606},{"date":"2018-11-24T06:00","casino":635,"sportbook":221,"other":236,"totalbet":6339},{"date":"2018-11-24T07:00","casino":608,"sportbook":221,"other":282,"totalbet":7436},{"date":"2018-11-24T08:00","casino":739,"sportbook":340,"other":260,"totalbet":6702},{"date":"2018-11-24T09:00","casino":617,"sportbook":213,"other":349,"totalbet":6225},{"date":"2018-11-24T10:00","casino":632,"sportbook":258,"other":303,"totalbet":6442},{"date":"2018-11-24T11:00","casino":619,"sportbook":204,"other":209,"totalbet":7953},{"date":"2018-11-24T12:00","casino":751,"sportbook":336,"other":229,"totalbet":6573},{"date":"2018-11-24T13:00","casino":640,"sportbook":252,"other":212,"totalbet":6494},{"date":"2018-11-24T14:00","casino":796,"sportbook":267,"other":321,"totalbet":7746},{"date":"2018-11-24T15:00","casino":788,"sportbook":326,"other":310,"totalbet":6299},{"date":"2018-11-24T16:00","casino":654,"sportbook":332,"other":267,"totalbet":7721},{"date":"2018-11-24T17:00","casino":781,"sportbook":267,"other":322,"totalbet":6973},{"date":"2018-11-24T18:00","casino":795,"sportbook":302,"other":291,"totalbet":7482},{"date":"2018-11-24T19:00","casino":697,"sportbook":210,"other":328,"totalbet":7468},{"date":"2018-11-24T20:00","casino":754,"sportbook":298,"other":253,"totalbet":6351},{"date":"2018-11-24T21:00","casino":706,"sportbook":245,"other":318,"totalbet":6674},{"date":"2018-11-24T22:00","casino":711,"sportbook":261,"other":290,"totalbet":7034},{"date":"2018-11-24T23:00","casino":724,"sportbook":217,"other":303,"totalbet":6288},{"date":"2018-11-25T00:00","casino":673,"sportbook":331,"other":340,"totalbet":7130},{"date":"2018-11-25T01:00","casino":721,"sportbook":217,"other":298,"totalbet":6095},{"date":"2018-11-25T02:00","casino":647,"sportbook":306,"other":310,"totalbet":6927},{"date":"2018-11-25T03:00","casino":681,"sportbook":279,"other":329,"totalbet":7004},{"date":"2018-11-25T04:00","casino":634,"sportbook":248,"other":301,"totalbet":7817},{"date":"2018-11-25T05:00","casino":692,"sportbook":326,"other":327,"totalbet":6500},{"date":"2018-11-25T06:00","casino":724,"sportbook":212,"other":321,"totalbet":7704},{"date":"2018-11-25T07:00","casino":768,"sportbook":317,"other":280,"totalbet":7793},{"date":"2018-11-25T08:00","casino":725,"sportbook":205,"other":288,"totalbet":6509},{"date":"2018-11-25T09:00","casino":609,"sportbook":314,"other":250,"totalbet":6403},{"date":"2018-11-25T10:00","casino":737,"sportbook":265,"other":245,"totalbet":7866},{"date":"2018-11-25T11:00","casino":619,"sportbook":283,"other":233,"totalbet":7069},{"date":"2018-11-25T12:00","casino":691,"sportbook":318,"other":200,"totalbet":6108},{"date":"2018-11-25T13:00","casino":629,"sportbook":300,"other":344,"totalbet":7861},{"date":"2018-11-25T14:00","casino":743,"sportbook":231,"other":216,"totalbet":6659},{"date":"2018-11-25T15:00","casino":747,"sportbook":244,"other":344,"totalbet":7819},{"date":"2018-11-25T16:00","casino":715,"sportbook":270,"other":268,"totalbet":6991},{"date":"2018-11-25T17:00","casino":653,"sportbook":263,"other":346,"totalbet":7623},{"date":"2018-11-25T18:00","casino":649,"sportbook":276,"other":204,"totalbet":6589},{"date":"2018-11-25T19:00","casino":627,"sportbook":335,"other":332,"totalbet":6198},{"date":"2018-11-25T20:00","casino":630,"sportbook":308,"other":225,"totalbet":7267},{"date":"2018-11-25T21:00","casino":762,"sportbook":250,"other":230,"totalbet":6568},{"date":"2018-11-25T22:00","casino":723,"sportbook":310,"other":292,"totalbet":7531},{"date":"2018-11-25T23:00","casino":793,"sportbook":251,"other":299,"totalbet":7242},{"date":"2018-11-26T00:00","casino":776,"sportbook":250,"other":303,"totalbet":7272},{"date":"2018-11-26T01:00","casino":682,"sportbook":209,"other":307,"totalbet":7421},{"date":"2018-11-26T02:00","casino":711,"sportbook":287,"other":220,"totalbet":7196},{"date":"2018-11-26T03:00","casino":670,"sportbook":254,"other":222,"totalbet":6881},{"date":"2018-11-26T04:00","casino":798,"sportbook":205,"other":325,"totalbet":6678},{"date":"2018-11-26T05:00","casino":642,"sportbook":278,"other":213,"totalbet":6098},{"date":"2018-11-26T06:00","casino":602,"sportbook":222,"other":236,"totalbet":7298},{"date":"2018-11-26T07:00","casino":752,"sportbook":279,"other":255,"totalbet":7923},{"date":"2018-11-26T08:00","casino":686,"sportbook":324,"other":322,"totalbet":6096},{"date":"2018-11-26T09:00","casino":710,"sportbook":299,"other":254,"totalbet":6815},{"date":"2018-11-26T10:00","casino":719,"sportbook":310,"other":234,"totalbet":6722},{"date":"2018-11-26T11:00","casino":799,"sportbook":223,"other":259,"totalbet":7066},{"date":"2018-11-26T12:00","casino":636,"sportbook":306,"other":276,"totalbet":7669},{"date":"2018-11-26T13:00","casino":786,"sportbook":240,"other":327,"totalbet":6555},{"date":"2018-11-26T14:00","casino":721,"sportbook":249,"other":250,"totalbet":7592},{"date":"2018-11-26T15:00","casino":698,"sportbook":261,"other":251,"totalbet":7372},{"date":"2018-11-26T16:00","casino":777,"sportbook":350,"other":314,"totalbet":6851},{"date":"2018-11-26T17:00","casino":734,"sportbook":337,"other":290,"totalbet":7447},{"date":"2018-11-26T18:00","casino":755,"sportbook":218,"other":211,"totalbet":6520},{"date":"2018-11-26T19:00","casino":663,"sportbook":329,"other":301,"totalbet":6060},{"date":"2018-11-26T20:00","casino":600,"sportbook":335,"other":315,"totalbet":6208},{"date":"2018-11-26T21:00","casino":799,"sportbook":235,"other":348,"totalbet":6968},{"date":"2018-11-26T22:00","casino":746,"sportbook":233,"other":333,"totalbet":6201},{"date":"2018-11-26T23:00","casino":691,"sportbook":337,"other":267,"totalbet":6161},{"date":"2018-11-27T00:00","casino":752,"sportbook":292,"other":262,"totalbet":7993},{"date":"2018-11-27T01:00","casino":654,"sportbook":258,"other":210,"totalbet":7015},{"date":"2018-11-27T02:00","casino":682,"sportbook":323,"other":245,"totalbet":6604},{"date":"2018-11-27T03:00","casino":665,"sportbook":259,"other":260,"totalbet":7773},{"date":"2018-11-27T04:00","casino":690,"sportbook":300,"other":276,"totalbet":6004},{"date":"2018-11-27T05:00","casino":716,"sportbook":218,"other":221,"totalbet":7957},{"date":"2018-11-27T06:00","casino":787,"sportbook":205,"other":334,"totalbet":6592},{"date":"2018-11-27T07:00","casino":747,"sportbook":330,"other":302,"totalbet":6889},{"date":"2018-11-27T08:00","casino":648,"sportbook":316,"other":331,"totalbet":6472},{"date":"2018-11-27T09:00","casino":783,"sportbook":240,"other":239,"totalbet":7217},{"date":"2018-11-27T10:00","casino":628,"sportbook":306,"other":338,"totalbet":6453},{"date":"2018-11-27T11:00","casino":642,"sportbook":289,"other":201,"totalbet":6130},{"date":"2018-11-27T12:00","casino":691,"sportbook":333,"other":251,"totalbet":6585},{"date":"2018-11-27T13:00","casino":719,"sportbook":344,"other":216,"totalbet":6831},{"date":"2018-11-27T14:00","casino":759,"sportbook":227,"other":247,"totalbet":6284},{"date":"2018-11-27T15:00","casino":632,"sportbook":350,"other":228,"totalbet":6105},{"date":"2018-11-27T16:00","casino":712,"sportbook":290,"other":246,"totalbet":6976},{"date":"2018-11-27T17:00","casino":624,"sportbook":287,"other":350,"totalbet":6330},{"date":"2018-11-27T18:00","casino":793,"sportbook":297,"other":311,"totalbet":7701},{"date":"2018-11-27T19:00","casino":796,"sportbook":293,"other":292,"totalbet":7397},{"date":"2018-11-27T20:00","casino":694,"sportbook":324,"other":231,"totalbet":6884},{"date":"2018-11-27T21:00","casino":755,"sportbook":283,"other":231,"totalbet":6817},{"date":"2018-11-27T22:00","casino":689,"sportbook":328,"other":243,"totalbet":7711},{"date":"2018-11-27T23:00","casino":685,"sportbook":212,"other":323,"totalbet":7798}]